CPU-v/src/verilog/core/instruction_decoder.v
`timescale 1ns/1ns
`define ClEAR_ALL_OUTPINTS \
    alu_op = 19'b0; \
    jmp_op = 9'b0; \
    mem_op = 9'b0; \
    cust_op = 1'b0; \
    csr_op = 6'b0; \
    mechie_op = 8'b0; \
    invalid_instruction = 32'bz; \

module instruction_decode(
    input en,
    input wire [31:0] instruction_code,
    output reg invalid_instruction,
    output reg [18:0] alu_op,
    output reg [8:0] jmp_op,
    output reg  [8:0] mem_op,
    output reg cust_op,
    output reg [5:0] csr_op,
    output reg [7:0] mechie_op,
    output wire [4:0] rd, rs1, rs2,
    output wire [6:0] imm_2531,//R-type
    output wire [19:0] imm_1231,//U-type
    output wire [11:0] imm_2032//I-type
);

wire [6:2] opcode;
wire [2:0] funct3;
assign opcode = instruction_code[6:2];
assign funct3 = instruction_code[14:12];
assign imm_2531 = en ? instruction_code[31:25] : 7'b0;
assign imm_1231 = en ? instruction_code[31:12] : 19'b0;
assign imm_2032 = en ? instruction_code[31:20] : 12'b0;
assign rd = en ? instruction_code[11:7] : 5'b0;
assign rs1 = en ? instruction_code[19:15] : 5'b0;
assign rs2 = en ? instruction_code[24:20] : 5'b0;
function [8:0] get_jmp_op(input [2:0]funct3);
    case(funct3)
        3'b000: get_jmp_op = 9'b000000000;//beq
        3'b001: get_jmp_op = 9'b000000001;//bne
        3'b100: get_jmp_op = 9'b000000010;//blt
        3'b101: get_jmp_op = 9'b000000011;//bge
        3'b110: get_jmp_op = 9'b000000100;//bltu
        3'b111: get_jmp_op = 9'b000000101;//bgeu
        default: begin
            get_jmp_op = 9'b0;
            invalid_instruction = 32'd2;
        end
    endcase
    
endfunction

    function [18:0] get_alu_op(input [2:0] funct3);
        case (funct3)
            3'b000: get_alu_op = instruction_code[30] ? 19'b1 << 1 : 19'b1;  //add/sub
            3'b001: get_alu_op = 19'b1 << 2;  // sll    
            3'b010: get_alu_op = 19'b1 << 3;  // slt  
            3'b011: get_alu_op = 19'b1 << 4;  // sltu
            3'b100: get_alu_op = 19'b1 << 5;  // xor
            3'b101: get_alu_op = instruction_code[30] ? 19'b1 << 7 : 19'b1 << 6; // srl/sra
            3'b110: get_alu_op = 19'b1 << 8;  // or
            3'b111: get_alu_op = 19'b1 << 9;  // and
            default: begin
                get_alu_op = 9'd0;
                invalid_instruction = 32'd2;
            end
        endcase
        endfunction
     function [18:0] get_alu1_op(input [2:0] funct3);
        case (funct3)
            3'b000: get_alu1_op = 19'b1 << 10;  //addi
            3'b001: get_alu1_op = 19'b1 << 11;  //slli
            3'b010: get_alu1_op = 19'b1 << 12;  //slti
            3'b011: get_alu1_op = 19'b1 << 13;  //sltiu
            3'b100: get_alu1_op = 19'b1 << 14;  //xori
            3'b101: get_alu1_op = instruction_code[30] ? 19'b1 << 16 : 19'b1 << 15; //srli/srai
            3'b110: get_alu1_op = 19'b1 << 17; //ori
            3'b111: get_alu1_op = 19'b1 << 18; //andi
            default: begin
                get_alu1_op = 9'd0;
                invalid_instruction = 32'd2;
            end
        endcase
    endfunction

    function [8:0] get_mem_load_op(input [2:0] funct3);
        case (funct3)
            3'b000: get_mem_load_op = 9'b000000010; //lb
            3'b001: get_mem_load_op = 9'b000000100; //lh
            3'b010: get_mem_load_op = 9'b000001000; //lw
            3'b100: get_mem_load_op = 9'b000010000; //lbu
            3'b101: get_mem_load_op = 9'b000100000; //lhu
            default: begin
                get_mem_load_op = 9'd0;
                invalid_instruction = 32'd2;
            end
        endcase
    endfunction

    function [8:0] get_mem_store_op(input [2:0] funct3);
        case (funct3)
            3'b000: get_mem_store_op = 9'b001000000; //sb
            3'b001: get_mem_store_op = 9'b010000000; //sh
            3'b010: get_mem_store_op = 9'b100000000; //sw
            default: begin
                get_mem_store_op = 9'd0;
                invalid_instruction = 32'd2;
            end
        endcase
    endfunction

    function [5:0] get_csr_op(input [2:0] funct3);
        case (funct3)
            3'b001: get_csr_op = 6'b000001; //csrrw
            3'b010: get_csr_op = 6'b000010; //csrrs
            3'b011: get_csr_op = 6'b000100; //csrrc
            3'b101: get_csr_op = 6'b001000; //csrrwi
            3'b110: get_csr_op = 6'b010000; //csrrsi
            3'b111: get_csr_op = 6'b100000; //csrrci
            default: begin
                get_csr_op = 6'd0;
                invalid_instruction = 32'd2;
            end
        endcase
    endfunction

    function [7:0] get_mechine_op(input [31:0] instruction_code);
        case (instruction_code)
            32'h10200073: get_mechine_op = 8'b00010000; //sret
            32'h10500073: get_mechine_op = 8'b00100000; //wfi
            32'h30200073: get_mechine_op = 8'b00000100; //mret
            32'h100073: get_mechine_op = 8'b00000001; //ebreak
            32'h73: get_mechine_op = 8'b00000010; //ecall
            default: begin
                get_mechine_op = 8'd0;
                invalid_instruction = 32'd2;
            end
        endcase
    endfunction



    always @(*) begin
        if(en) begin
            `ClEAR_ALL_OUTPINTS;
            if(instruction_code[1:0] != 2'b11)begin
                invalid_instruction = 32'd2;
            end
            else begin
        case(opcode)
                    7'b11000:begin
                        jmp_op = get_jmp_op(funct3);
                    end
                    7'b11001:begin
                        if (funct3 == 3'b000) begin
                        jmp_op = 9'b000000110; //jalr
                    end
                    end
                    7'b11011: begin // jal
                        jmp_op = 9'b000000001;
                    end
                    7'b00101: begin 
                        jmp_op = 9'b100000000; //auipc
                    end
                    7'b00100: begin
                        alu_op = get_alu1_op(funct3);
                    end
                    7'b01100: begin
                        alu_op = get_alu_op(funct3);
                    end
                    7'b01101: begin
                        mem_op = 9'b000000001; //lui
                    end
                    7'b00000: begin
                        mem_op = get_mem_load_op(funct3);
                    end
                    7'b01000: begin
                        mem_op = get_mem_store_op(funct3);
                    end
                    7'b11100: begin
                        if (funct3 == 3'b000) begin
                            mechie_op = get_mechine_op(instruction_code);
                        end
                        else begin
                            csr_op = get_csr_op(funct3);
                        end
                    end
                    7'b11111: begin
                        cust_op = 1'b1;
                    end
                    default: begin
                        invalid_instruction = 32'd2;
                    end
            endcase
        end
    end
        else begin
                `ClEAR_ALL_OUTPINTS
            end
        end
endmodule

CPU-v/.history/src/verilog/tb_instdecoder_20250225104044.v
/*                                                                      

*/
`timescale 1ns/1ns
`include "instruction_decoder.v"

module instdecoder_tb();
    reg [31:0] instruction_code;
    reg en;
    wire invalid_instruction;
    wire [18:0] alu_op;
    wire  [8:0] jmp_op;
    wire [8:0] mem_op;
    wire cust_op;
    wire [5:0] csr_op;
    wire [7:0] mechie_op;
    wire [4:0] rd; 
    wire [4:0] rs1; 
    wire [4:0] rs2;
    wire [6:0] imm_2531;
    wire [19:0] imm_1231;
    wire [11:0] imm_2032;

    instruction_decode dut(
        .instruction_code(instruction_code),
        .en(en),
        .invalid_instruction(invalid_instruction),
        .alu_op(alu_op),
        .jmp_op(jmp_op),
        .mem_op(mem_op),
        .cust_op(cust_op),
        .csr_op(csr_op),
        .mechie_op(mechie_op),
        .rd(rd),
        .rs1(rs1),
        .rs2(rs2),
        .imm_2531(imm_2531),
        .imm_1231(imm_1231),
        .imm_2032(imm_2032)
    );


`ifdef FSDB
initial begin
    $Dumpfile("tb_instru.fsdb");
    $Dumpvars;
end
`endif

    initial begin
        en = 1;
        instruction_code = 32'd0; // invalid instruction
        #200;
        instruction_code = 32'h00000797;  // auipc	a5,0x0
        #200;
        instruction_code = 32'd0; 
        #10;
        instruction_code = 32'h02c78793;  // addi	a5,a5,44
        #200;
        instruction_code = 32'd0; 
        #10;
        instruction_code = 32'h305793f3; // csrrw	t2,mtvec,a5
        #200;
        instruction_code = 32'd0; 
        #10;
        instruction_code = 32'h1a5000ef; // jal	20009c4
        #200;
        instruction_code = 32'd0; 
        #10;
        instruction_code = 32'h00112623; // sw	ra,12(sp)
        #200;
        instruction_code = 32'd0; 
        #10;
        instruction_code = 32'h30200073; // mret
        #200;
        instruction_code = 32'd0; 
        #10;
        instruction_code = 32'h04079263; // bnez	a5,20000cc  (bne rs,x0,offset)
        #200;
        instruction_code = 32'd0; 
        #10;
        instruction_code = 32'h07f56513; // ori	a0,a0,127
        #200;
        instruction_code = 32'd0; 
        #10;
        instruction_code = 32'h8000007F; // cust op
        #200;
        $finish;
    end


endmodule

CPU-v/src/verilog/core/tb_instru.vcd
$date
	Tue Feb 25 10:47:15 2025
$end
$version
	Icarus Verilog
$end
$timescale
	1ns
$end
$scope module instdecoder_tb $end
$var wire 5 ! rs2 [4:0] $end
$var wire 5 " rs1 [4:0] $end
$var wire 5 # rd [4:0] $end
$var wire 9 $ mem_op [8:0] $end
$var wire 8 % mechie_op [7:0] $end
$var wire 9 & jmp_op [8:0] $end
$var wire 1 ' invalid_instruction $end
$var wire 7 ( imm_2531 [6:0] $end
$var wire 12 ) imm_2032 [11:0] $end
$var wire 20 * imm_1231 [19:0] $end
$var wire 1 + cust_op $end
$var wire 6 , csr_op [5:0] $end
$var wire 19 - alu_op [18:0] $end
$var reg 1 . en $end
$var reg 32 / instruction_code [31:0] $end
$scope module dut $end
$var wire 1 . en $end
$var wire 32 0 instruction_code [31:0] $end
$var wire 5 1 rs2 [4:0] $end
$var wire 5 2 rs1 [4:0] $end
$var wire 5 3 rd [4:0] $end
$var wire 5 4 opcode [6:2] $end
$var wire 7 5 imm_2531 [6:0] $end
$var wire 12 6 imm_2032 [11:0] $end
$var wire 20 7 imm_1231 [19:0] $end
$var wire 3 8 funct3 [2:0] $end
$var reg 19 9 alu_op [18:0] $end
$var reg 6 : csr_op [5:0] $end
$var reg 1 + cust_op $end
$var reg 1 ' invalid_instruction $end
$var reg 9 ; jmp_op [8:0] $end
$var reg 8 < mechie_op [7:0] $end
$var reg 9 = mem_op [8:0] $end
$scope function get_alu1_op $end
$var reg 3 > funct3 [2:0] $end
$upscope $end
$scope function get_alu_op $end
$var reg 3 ? funct3 [2:0] $end
$upscope $end
$scope function get_csr_op $end
$var reg 3 @ funct3 [2:0] $end
$upscope $end
$scope function get_jmp_op $end
$var reg 3 A funct3 [2:0] $end
$upscope $end
$scope function get_mechine_op $end
$var reg 32 B instruction_code [31:0] $end
$upscope $end
$scope function get_mem_load_op $end
$var reg 3 C funct3 [2:0] $end
$upscope $end
$scope function get_mem_store_op $end
$var reg 3 D funct3 [2:0] $end
$upscope $end
$upscope $end
$upscope $end
$enddefinitions $end
$comment Show the parameter values. $end
$dumpall
$end
#0
$dumpvars
bx D
bx C
bx B
bx A
bx @
bx ?
bx >
b0 =
b0 <
b0 ;
b0 :
b0 9
b0 8
b0 7
b0 6
b0 5
b0 4
b0 3
b0 2
b0 1
b0 0
b0 /
1.
b0 -
b0 ,
0+
b0 *
b0 )
b0 (
0'
b0 &
b0 %
b0 $
b0 #
b0 "
b0 !
$end
#200
b1111 #
b1111 3
b100000000 &
b100000000 ;
z'
b101 4
b11110010111 /
b11110010111 0
#400
b0 #
b0 3
0'
b0 &
b0 ;
b0 4
b0 /
b0 0
#410
b1 (
b1 5
b10110001111000 *
b10110001111000 7
b101100 )
b101100 6
b1111 #
b1111 3
b1111 "
b1111 2
b1100 !
b1100 1
b10000000000 -
b10000000000 9
b0 >
z'
b100 4
b10110001111000011110010011 /
b10110001111000011110010011 0
#610
b0 (
b0 5
b0 *
b0 7
b0 )
b0 6
b0 #
b0 3
b0 "
b0 2
b0 !
b0 1
0'
b0 -
b0 9
b0 4
b0 /
b0 0
#620
b11000 (
b11000 5
b110000010101111001 *
b110000010101111001 7
b1100000101 )
b1100000101 6
b111 #
b111 3
b1111 "
b1111 2
b101 !
b101 1
b1 ,
b1 :
b1 @
z'
b11100 4
b1 8
b110000010101111001001111110011 /
b110000010101111001001111110011 0
#820
b0 (
b0 5
b0 *
b0 7
b0 )
b0 6
b0 #
b0 3
b0 "
b0 2
b0 !
b0 1
0'
b0 ,
b0 :
b0 4
b0 8
b0 /
b0 0
#830
b1101 (
b1101 5
b11010010100000000 *
b11010010100000000 7
b110100101 )
b110100101 6
b1 #
b1 3
b101 !
b101 1
b1 &
b1 ;
z'
b11011 4
b11010010100000000000011101111 /
b11010010100000000000011101111 0
#1030
b0 (
b0 5
b0 *
b0 7
b0 )
b0 6
b0 #
b0 3
b0 !
b0 1
0'
b0 &
b0 ;
b0 4
b0 /
b0 0
#1040
b100010010 *
b100010010 7
b1 )
b1 6
b1100 #
b1100 3
b10 "
b10 2
b1 !
b1 1
b100000000 $
b100000000 =
b10 D
z'
b1000 4
b10 8
b100010010011000100011 /
b100010010011000100011 0
#1240
b0 *
b0 7
b0 )
b0 6
b0 #
b0 3
b0 "
b0 2
b0 !
b0 1
0'
b0 $
b0 =
b0 4
b0 8
b0 /
b0 0
#1250
b11000 (
b11000 5
b110000001000000000 *
b110000001000000000 7
b1100000010 )
b1100000010 6
b10 !
b10 1
b100 %
b100 <
b110000001000000000000001110011 B
z'
b11100 4
b110000001000000000000001110011 /
b110000001000000000000001110011 0
#1450
b0 (
b0 5
b0 *
b0 7
b0 )
b0 6
b0 !
b0 1
0'
b0 %
b0 <
b0 4
b0 /
b0 0
#1460
b10 (
b10 5
b100000001111001 *
b100000001111001 7
b1000000 )
b1000000 6
b100 #
b100 3
b1111 "
b1111 2
b1 &
b1 ;
b1 A
z'
b11000 4
b1 8
b100000001111001001001100011 /
b100000001111001001001100011 0
#1660
b0 (
b0 5
b0 *
b0 7
b0 )
b0 6
b0 #
b0 3
b0 "
b0 2
0'
b0 &
b0 ;
b0 4
b0 8
b0 /
b0 0
#1670
b11 (
b11 5
b111111101010110 *
b111111101010110 7
b1111111 )
b1111111 6
b1010 #
b1010 3
b1010 "
b1010 2
b11111 !
b11111 1
b100000000000000000 -
b100000000000000000 9
b110 >
z'
b100 4
b110 8
b111111101010110010100010011 /
b111111101010110010100010011 0
#1870
b0 (
b0 5
b0 *
b0 7
b0 )
b0 6
b0 #
b0 3
b0 "
b0 2
b0 !
b0 1
0'
b0 -
b0 9
b0 4
b0 8
b0 /
b0 0
#1880
b1000000 (
b1000000 5
b10000000000000000000 *
b10000000000000000000 7
b100000000000 )
b100000000000 6
1+
z'
b11111 4
b10000000000000000000000001111111 /
b10000000000000000000000001111111 0
