CPU-v/src/verilog/review/Re_instruction_decoder.v
`define CLEAR_ALL_OUTPINS \
    invalid_instruction = 1'b0; \
    inst_beq = 1'b0; \
    inst_bge = 1'b0; \
    inst_bgeu = 1'b0; \
    inst_blt = 1'b0; \
    inst_bltu = 1'b0; \
    inst_bne = 1'b0; \
    inst_addi = 1'b0; \
    inst_andi = 1'b0; \
    inst_csrrc = 1'b0; \
    inst_csrrci = 1'b0; \
    inst_csrrs = 1'b0; \
    inst_csrrsi = 1'b0; \
    inst_csrrw = 1'b0; \
    inst_csrrwi = 1'b0; \
    inst_ebreak = 1'b0; \
    inst_ecall = 1'b0; \
    inst_jalr = 1'b0; \
    inst_lb = 1'b0; \
    inst_lbu = 1'b0; \
    inst_lh = 1'b0; \
    inst_lhu = 1'b0; \
    inst_lw = 1'b0; \
    inst_ori = 1'b0; \
    inst_slli = 1'b0; \
    inst_slti = 1'b0; \
    inst_sltiu = 1'b0; \
    inst_srai = 1'b0; \
    inst_srli = 1'b0; \
    inst_xori = 1'b0; \
    inst_jal = 1'b0; \
    inst_add = 1'b0; \
    inst_and = 1'b0; \
    inst_mret = 1'b0; \
    inst_or = 1'b0; \
    inst_sll = 1'b0; \
    inst_slt = 1'b0; \
    inst_sltu = 1'b0; \
    inst_sra = 1'b0; \
    inst_sret = 1'b0; \
    inst_srl = 1'b0; \
    inst_sub = 1'b0; \
    inst_wfi = 1'b0; \
    inst_xor = 1'b0; \
    inst_sb = 1'b0; \
    inst_sh = 1'b0; \
    inst_sw = 1'b0; \
    inst_auipc = 1'b0; \
    inst_lui = 1'b0; 

module instruction_decoder(
    input en,
    input wire [31:0] instruction_code,
    output wire [4:0] rd, rs1, rs2,
    output reg invalid_instruction,
    output [47:0] inst_flags

    // output [6:0] imm_2531,//R-type
    // output wire[19:0] imm_1231,//U-type
    // output [11:0] imm_2032//I-type
);

 	reg inst_beq;
    reg inst_bge;
    reg inst_bgeu;
    reg inst_blt;
    reg inst_bltu;
    reg inst_bne;
    reg inst_addi;
    reg inst_slti;
    reg inst_sltiu;
    reg inst_xori;
    reg inst_ori;
    reg inst_andi;
    reg inst_slli;
    reg inst_srli;
    reg inst_srai;
    reg inst_add;
    reg inst_sub;
    reg inst_sll;
    reg inst_slt;
    reg inst_sltu;
    reg inst_xor;
    reg inst_or;
    reg inst_and;
    reg inst_lb;
    reg inst_lh;
    reg inst_lw;
    reg inst_lbu;
    reg inst_lhu;
    reg inst_sb;
    reg inst_sh;
    reg inst_sw;
    reg inst_csrrw;
    reg inst_csrrs;
    reg inst_csrrc;
    reg inst_csrrwi;
    reg inst_csrrsi;
    reg inst_csrrci;
    reg inst_sret;
    reg inst_wfi;
    reg inst_mret;
    reg inst_ecall;
    reg inst_ebreak;
    reg inst_jalr;
    reg inst_jal;
    reg inst_auipc;
    reg inst_lui;
    reg inst_sra;
    reg inst_srl;

    wire [4:0] opcode;
    wire [2:0] funct3;  





    assign opcode = instruction_code[6:2];//最低两位都是11不需要管
    assign funct3 = instruction_code[14:12];
    // assign imm25_31 = en? instruction_code[31:25]:7'b0;
    // assign imm20_31 = en? instruction_code[31:20]:12'b0;
    assign imm12_31 = en? instruction_code[31:12]:19'b0;
    assign rd = en? instruction_code[11:7]:5'b0;
    assign rs1 = en? instruction_code[19:15]:5'b0;
    assign rs2 = en? instruction_code[24:20]:5'b0;

   assign inst_flags = {inst_wfi,inst_sret,inst_mret,inst_ecall,inst_ebreak,inst_csrrwi,inst_csrrw,inst_csrrsi,inst_csrrs,inst_csrrci,inst_csrrc,inst_sw,inst_sh,inst_sb,inst_lw,inst_lhu,inst_lh,inst_lbu,inst_lb,inst_lui,inst_xor,inst_sub,inst_srl,inst_sra,inst_sltu,inst_slt,inst_sll,inst_or,inst_and,inst_add,inst_xori,inst_srli,inst_srai,inst_sltiu,inst_slti,inst_slli,inst_ori,inst_andi,inst_addi,inst_auipc,inst_jal,inst_jalr,inst_bne,inst_bltu,inst_blt,inst_bgeu,inst_bge,inst_beq};

    task  get_jmp_op;
        case(funct3)
            3'b000: inst_beq = 1;
            3'b001: inst_bne = 1;
            3'b100: inst_blt = 1;
            3'b101: inst_bge = 1;
            3'b110: inst_bltu = 1;
            3'b111: inst_bgeu = 1;
            default: begin
                invalid_instruction = 1;
            end
        endcase
    endtask
    
    task get_alu_op;
        case(funct3)
            3'b000: begin
                inst_add = instruction_code[30]? 1'b0:1'b1;
                inst_sub = instruction_code[30]? 1'b1:1'b0;
            end
            3'b001: inst_sll = 1'b1;
            3'b010: inst_slt = 1'b1;
            3'b011: inst_sltu = 1'b1;
            3'b100: inst_xor = 1'b1;
            3'b101: begin 
                inst_srl = instruction_code[30]? 1'b0:1'b1;
                inst_sra = instruction_code[30]? 1'b1:1'b0;
            end
            3'b110: inst_or = 1'b1;
            3'b111: inst_and = 1'b1;
            default: begin
                invalid_instruction = 1;
            end
        endcase
    endtask

    task get_alu1_op;
        case(funct3)
            3'b000: inst_addi = 1;
            3'b001: inst_slli = 1;
            3'b010: inst_slti = 1;
            3'b011: inst_sltiu = 1;
            3'b100: inst_xori = 1;
            3'b101: begin
                inst_srli = instruction_code[30]? 1'b0:1'b1;
                inst_srai = instruction_code[30]? 1'b1:1'b0;
            end
            3'b110: inst_ori = 1;
            3'b111: inst_andi = 1;
            default: begin
                invalid_instruction = 1;
            end
        endcase
    endtask

    task get_mem_load_op;
        case(funct3)
            3'b000: inst_lb = 1;
            3'b001: inst_lh = 1;
            3'b010: inst_lw = 1;
            3'b100: inst_lbu = 1;
            3'b101: inst_lhu = 1;
            default: begin
                invalid_instruction = (instruction_code == 32'd0)? 1'd0:1'd1;
            end
        endcase
    endtask

    task get_mem_store_op;
        case(funct3)
            3'b000: inst_sb = 1;
            3'b001: inst_sh = 1;
            3'b010: inst_sw = 1;
            default: begin
                invalid_instruction = 1;
            end
        endcase
    endtask

    task get_csr_op;
        case(funct3)
            3'b001: inst_csrrw = 1;
            3'b010: inst_csrrs = 1;
            3'b011: inst_csrrc = 1;
            3'b101: inst_csrrwi = 1;
            3'b110: inst_csrrsi = 1;
            3'b111: inst_csrrci = 1;
            default: begin
                invalid_instruction = 1;
            end
        endcase
    endtask

    task get_mechine_op;
        case(instruction_code)
          32'h10200073: inst_sret = 1'b1;
          32'h10500073: inst_wfi = 1'b1;
            32'h30200073: inst_mret = 1'b1;
            32'h100073: inst_ecall = 1'b1;
            32'h73: inst_ecall = 1'b1;
            default: begin
                invalid_instruction = 1;
            end
        endcase
    endtask

    always @(*) begin
        if (en) begin
            `CLEAR_ALL_OUTPINS;
            if(instruction_code[1:0] != 2'b11) begin
                invalid_instruction = (instruction_code == 32'd0)? 1'd0:1'd1;
            end
        else begin
        case(opcode)
        5'b11000: begin
            get_jmp_op();
        end
        5'b11011: begin
            inst_jal = 1;
        end
        5'b11001:begin
            if (funct3 == 3'b000) begin
                inst_jalr = 1;
            end
        end
        5'b00101:begin
            inst_auipc = 1'b1;
        end
        5'b01101:begin
            inst_lui = 1'b1;
        end
        5'b01100:begin
            get_alu_op();
        end
        5'b00100:begin
            get_alu1_op();
        end
        5'b00000:begin
            get_mem_load_op();
        end
        5'b01000:begin
            get_mem_store_op();
        end
        5'b11100:begin
            if (funct3 == 3'b000) begin
                get_mechine_op();
            end
            else begin
            get_csr_op();
            end
        end
        default: begin
            invalid_instruction = (instruction_code == 32'd0)? 1'd0:1'd1;
        end
        endcase
    end
end
else begin
    invalid_instruction = 1;
end
end

endmodule

CPU-v/src/verilog/review/Re_tb_instr_decoder.v
`timescale 1ns/1ns
`include "Re_instruction_decoder.v"

module instdecoder_tb();
    reg [31:0] instruction_code;
    reg en;
    wire invalid_instruction;
    wire [4:0] rd; 
    wire [4:0] rs1; 
    wire [4:0] rs2;
    wire [47:0] inst_flags;


    instruction_decoder dut(
        .instruction_code(instruction_code),
        .en(en),
        .invalid_instruction(invalid_instruction),
        .rd(rd),
        .rs1(rs1),
        .rs2(rs2),
        .inst_flags(inst_flags)

    );

    initial begin
        $dumpfile("./res/instdecoder.vcd");
        $dumpvars(0, instdecoder_tb);
    end

    initial begin
        en = 1;
        instruction_code = 32'd0; // invalid instruction
        #200;
        instruction_code = 32'h00000797;  // auipc	a5,0x0
        #200;
        instruction_code = 32'd0; 
        #10;
        instruction_code = 32'h02c78793;  // addi	a5,a5,44
        #200;
        instruction_code = 32'd0; 
        #10;
        instruction_code = 32'h305793f3; // csrrw	t2,mtvec,a5
        #200;
        instruction_code = 32'd0; 
        #10;
        instruction_code = 32'h1a5000ef; // jal	20009c4
        #200;
        instruction_code = 32'd0; 
        #10;
        instruction_code = 32'h00112623; // sw	ra,12(sp)
        #200;
        instruction_code = 32'd0; 
        #10;
        instruction_code = 32'h30200073; // mret
        #200;
        instruction_code = 32'd0; 
        #10;
        instruction_code = 32'h04079263; // bnez	a5,20000cc  (bne rs,x0,offset)
        #200;
        instruction_code = 32'd0; 
        #10;
        instruction_code = 32'h07f56513; // ori	a0,a0,127
        #200;
        instruction_code = 32'd0; 
        #10;
        instruction_code = 32'h8000007F; // cust op
        #200;
        $finish;
    end


endmodule

CPU-v/src/verilog/review/instdecoder.vcd
$date
	Wed Feb 26 11:01:04 2025
$end
$version
	Icarus Verilog
$end
$timescale
	1ns
$end
$scope module instdecoder_tb $end
$var wire 5 ! rs2 [4:0] $end
$var wire 5 " rs1 [4:0] $end
$var wire 5 # rd [4:0] $end
$var wire 1 $ invalid_instruction $end
$var wire 48 % inst_flags [47:0] $end
$var reg 1 & en $end
$var reg 32 ' instruction_code [31:0] $end
$scope module dut $end
$var wire 1 & en $end
$var wire 32 ( instruction_code [31:0] $end
$var wire 5 ) rs2 [4:0] $end
$var wire 5 * rs1 [4:0] $end
$var wire 5 + rd [4:0] $end
$var wire 5 , opcode [4:0] $end
$var wire 48 - inst_flags [47:0] $end
$var wire 1 . imm12_31 $end
$var wire 3 / funct3 [2:0] $end
$var reg 1 0 inst_add $end
$var reg 1 1 inst_addi $end
$var reg 1 2 inst_and $end
$var reg 1 3 inst_andi $end
$var reg 1 4 inst_auipc $end
$var reg 1 5 inst_beq $end
$var reg 1 6 inst_bge $end
$var reg 1 7 inst_bgeu $end
$var reg 1 8 inst_blt $end
$var reg 1 9 inst_bltu $end
$var reg 1 : inst_bne $end
$var reg 1 ; inst_csrrc $end
$var reg 1 < inst_csrrci $end
$var reg 1 = inst_csrrs $end
$var reg 1 > inst_csrrsi $end
$var reg 1 ? inst_csrrw $end
$var reg 1 @ inst_csrrwi $end
$var reg 1 A inst_ebreak $end
$var reg 1 B inst_ecall $end
$var reg 1 C inst_jal $end
$var reg 1 D inst_jalr $end
$var reg 1 E inst_lb $end
$var reg 1 F inst_lbu $end
$var reg 1 G inst_lh $end
$var reg 1 H inst_lhu $end
$var reg 1 I inst_lui $end
$var reg 1 J inst_lw $end
$var reg 1 K inst_mret $end
$var reg 1 L inst_or $end
$var reg 1 M inst_ori $end
$var reg 1 N inst_sb $end
$var reg 1 O inst_sh $end
$var reg 1 P inst_sll $end
$var reg 1 Q inst_slli $end
$var reg 1 R inst_slt $end
$var reg 1 S inst_slti $end
$var reg 1 T inst_sltiu $end
$var reg 1 U inst_sltu $end
$var reg 1 V inst_sra $end
$var reg 1 W inst_srai $end
$var reg 1 X inst_sret $end
$var reg 1 Y inst_srl $end
$var reg 1 Z inst_srli $end
$var reg 1 [ inst_sub $end
$var reg 1 \ inst_sw $end
$var reg 1 ] inst_wfi $end
$var reg 1 ^ inst_xor $end
$var reg 1 _ inst_xori $end
$var reg 1 $ invalid_instruction $end
$scope task get_alu1_op $end
$upscope $end
$scope task get_alu_op $end
$upscope $end
$scope task get_csr_op $end
$upscope $end
$scope task get_jmp_op $end
$upscope $end
$scope task get_mechine_op $end
$upscope $end
$scope task get_mem_load_op $end
$upscope $end
$scope task get_mem_store_op $end
$upscope $end
$upscope $end
$upscope $end
$enddefinitions $end
$comment Show the parameter values. $end
$dumpall
$end
#0
$dumpvars
0_
0^
0]
0\
0[
0Z
0Y
0X
0W
0V
0U
0T
0S
0R
0Q
0P
0O
0N
0M
0L
0K
0J
0I
0H
0G
0F
0E
0D
0C
0B
0A
0@
0?
0>
0=
0<
0;
0:
09
08
07
06
05
04
03
02
01
00
b0 /
0.
b0 -
b0 ,
b0 +
b0 *
b0 )
b0 (
b0 '
1&
b0 %
0$
b0 #
b0 "
b0 !
$end
#200
b1111 #
b1111 +
b100000000 %
b100000000 -
14
b101 ,
b11110010111 '
b11110010111 (
#400
b0 #
b0 +
b0 %
b0 -
04
b0 ,
b0 '
b0 (
#410
b1111 #
b1111 +
b1111 "
b1111 *
b1100 !
b1100 )
b1000000000 %
b1000000000 -
11
b100 ,
b10110001111000011110010011 '
b10110001111000011110010011 (
#610
b0 #
b0 +
b0 "
b0 *
b0 !
b0 )
b0 %
b0 -
01
b0 ,
b0 '
b0 (
#620
1.
b111 #
b111 +
b1111 "
b1111 *
b101 !
b101 )
b100000000000000000000000000000000000000000 %
b100000000000000000000000000000000000000000 -
1?
b11100 ,
b1 /
b110000010101111001001111110011 '
b110000010101111001001111110011 (
#820
0.
b0 #
b0 +
b0 "
b0 *
b0 !
b0 )
b0 %
b0 -
0?
b0 ,
b0 /
b0 '
b0 (
#830
b1 #
b1 +
b101 !
b101 )
b10000000 %
b10000000 -
1C
b11011 ,
b11010010100000000000011101111 '
b11010010100000000000011101111 (
#1030
b0 #
b0 +
b0 !
b0 )
b0 %
b0 -
0C
b0 ,
b0 '
b0 (
#1040
b1100 #
b1100 +
b10 "
b10 *
b1 !
b1 )
b1000000000000000000000000000000000000 %
b1000000000000000000000000000000000000 -
1\
b1000 ,
b10 /
b100010010011000100011 '
b100010010011000100011 (
#1240
b0 #
b0 +
b0 "
b0 *
b0 !
b0 )
b0 %
b0 -
0\
b0 ,
b0 /
b0 '
b0 (
#1250
b10 !
b10 )
b1000000000000000000000000000000000000000000000 %
b1000000000000000000000000000000000000000000000 -
1K
b11100 ,
b110000001000000000000001110011 '
b110000001000000000000001110011 (
#1450
b0 !
b0 )
b0 %
b0 -
0K
b0 ,
b0 '
b0 (
#1460
1.
b100 #
b100 +
b1111 "
b1111 *
b100000 %
b100000 -
1:
b11000 ,
b1 /
b100000001111001001001100011 '
b100000001111001001001100011 (
#1660
0.
b0 #
b0 +
b0 "
b0 *
b0 %
b0 -
0:
b0 ,
b0 /
b0 '
b0 (
#1670
b1010 #
b1010 +
b1010 "
b1010 *
b11111 !
b11111 )
b100000000000 %
b100000000000 -
1M
b100 ,
b110 /
b111111101010110010100010011 '
b111111101010110010100010011 (
#1870
b0 #
b0 +
b0 "
b0 *
b0 !
b0 )
b0 %
b0 -
0M
b0 ,
b0 /
b0 '
b0 (
#1880
1$
b11111 ,
b10000000000000000000000001111111 '
b10000000000000000000000001111111 (
